ragenv_tools/__init__.py
ragenv_tools/data_loader.py
ragenv_tools/data_retriever.py
ragenv_tools/email.py
ragenv_tools/llm_answer.py
ragenv_tools/my_embedding.py
ragenv_tools/utils.py
ragenv_tools-0.0.2.dist-info/LICENSE
ragenv_tools-0.0.2.dist-info/METADATA
ragenv_tools-0.0.2.dist-info/WHEEL
ragenv_tools-0.0.2.dist-info/top_level.txt
ragenv_tools-0.0.2.dist-info/RECORD
