Metadata-Version: 2.1
Name: ragenv_tools
Version: 0.0.2
Summary: Useful Tools for Database, RAG and LLM
Author: ScottHu
Author-email: ScottHu <scotthu1999@foxmail.com>
Classifier: Programming Language :: Python :: 3
Classifier: License :: OSI Approved :: MIT License
Classifier: Operating System :: OS Independent
Requires-Python: >=3.11
License-File: LICENSE
